[{"name": "ueno", "name#ja": "\u4e0a\u91ce", "name#zh": "\u4e0a\u91ce", "author": "Typlog", "repo": "typlog/ueno", "version": "0.4.2", "tags": ["blog", "podcast"], "images": ["https://user-images.githubusercontent.com/290496/133878072-0286669c-2cc8-4976-99d2-2a59b7181bd5.png"], "id": "ueno", "avatar": "https://avatars.githubusercontent.com/u/26949884?v=4", "stars": 1}, {"name": "nezu", "name#ja": "\u6839\u6d25", "name#zh": "\u6839\u6d25", "author": "Typlog", "repo": "typlog/nezu", "version": "0.4.2", "tags": ["blog", "podcast"], "images": ["https://user-images.githubusercontent.com/290496/133878159-69f77262-26d9-426a-b984-8e72b551f5f3.png"], "id": "nezu", "avatar": "https://avatars.githubusercontent.com/u/26949884?v=4", "stars": 2}, {"name": "ginza", "name#ja": "\u9280\u5ea7", "name#zh": "\u94f6\u5ea7", "author": "Typlog", "repo": "typlog/ginza", "version": "0.4.2", "tags": ["blog", "podcast"], "images": ["https://user-images.githubusercontent.com/290496/133878214-faf64fa7-02b3-49df-ab79-601366a19422.png"], "id": "ginza", "avatar": "https://avatars.githubusercontent.com/u/26949884?v=4", "stars": 2}, {"name": "meguro", "name#zh": "\u76ee\u9ed1", "name#ja": "\u76ee\u9ed2", "repo": "typlog/meguro", "version": "0.3.1", "author": "Typlog", "tags": ["blog"], "images": ["https://user-images.githubusercontent.com/290496/137299261-e56658ae-29af-4b7d-a3ac-ce4aa348c915.png"], "id": "meguro", "avatar": "https://avatars.githubusercontent.com/u/26949884?v=4", "stars": 0}, {"name": "akasaka", "name#ja": "\u8d64\u5742", "name#zh": "\u8d64\u5742", "author": "Typlog", "repo": "typlog/akasaka", "version": "0.3.1", "preview": "https://docs.typlog.com/", "templates": ["home.j2", "item.j2", "list.j2", "lang.j2"], "tags": ["doc"], "images": ["https://user-images.githubusercontent.com/290496/143881184-a7427865-d1c7-472e-9dc0-d28beb38cf62.png", "https://user-images.githubusercontent.com/290496/143881498-a996ead3-ca3c-47a6-9048-a593f055c1e7.png"], "id": "akasaka", "avatar": "https://avatars.githubusercontent.com/u/26949884?v=4", "stars": 0}, {"name": "coffee", "name#zh": "\u5496\u5561", "name#ja": "\u30b3\u30fc\u30d2\u30fc", "description": "A podcast theme designed by uxcoffee.", "repo": "lepture/typlog-coffee", "version": "0.3.1", "author": "Hsiaoming Yang", "images": ["https://user-images.githubusercontent.com/290496/144819329-d42a0cd7-2b90-439b-85e8-d74783a51d4a.png", "https://user-images.githubusercontent.com/290496/144819322-415c9567-678d-410a-8a19-a529d06f8a4c.png", "https://user-images.githubusercontent.com/290496/144819338-f57c5259-94c5-4cf7-a162-d2a906a2ecb4.png"], "tags": ["podcast"], "site": {"id": 3010, "name": "Coffee", "primary_links": [{"title": "By tag", "url": "/topic/design/"}, {"title": "By host", "url": "/by/cat/"}, {"title": "Elements", "url": "/posts/elements"}, {"title": "Source code", "url": "https://github.com/lepture/typlog-coffee"}]}, "id": "coffee", "avatar": "https://avatars.githubusercontent.com/u/290496?v=4", "stars": 1}, {"name": "puti", "name#zh": "\u83e9\u63d0", "name#ja": "\u83e9\u63d0", "description": "A blog theme designed by Caicai.", "repo": "jessuni/typlog-puti", "version": "0.1.2", "author": "Jessie Ji", "tags": ["blog"], "images": ["https://user-images.githubusercontent.com/290496/158343805-0a62c4a4-a4ef-4784-b5f2-7d2723cc6fc0.png"], "id": "puti", "avatar": "https://avatars.githubusercontent.com/u/41285428?v=4", "stars": 1}]