{"name": "ueno", "name#ja": "\u4e0a\u91ce", "name#zh": "\u4e0a\u91ce", "author": "Typlog", "repo": "typlog/ueno", "features": {"post": true, "audio": true, "review": true}, "images": ["images/1.jpg", "images/2.jpg", "images/3.jpg", "images/4.jpg"], "avatar": "https://avatars.githubusercontent.com/u/26949884?v=4", "stars": 0, "readme": "<div id=\"readme\" class=\"md\" data-path=\"README.md\"><article class=\"markdown-body entry-content container-lg\" itemprop=\"text\"><h1>ueno</h1>\n</article></div>"}